setup.py
epubsearcher/__init__.py
epubsearcher/main.py
epubsearcher/search.py
epubsearcher/test.py
epubsearcher.egg-info/PKG-INFO
epubsearcher.egg-info/SOURCES.txt
epubsearcher.egg-info/dependency_links.txt
epubsearcher.egg-info/requires.txt
epubsearcher.egg-info/top_level.txt
epubsearcher/epubsearch/__init__.py
epubsearcher/epubsearch/epubindexer.py
epubsearcher/epubsearch/epubparser.py
epubsearcher/epubsearch/wordmorpho.py
epubsearcher/epubsearch/morpho_engines/__init__.py
epubsearcher/epubsearch/morpho_engines/baseengine.py
epubsearcher/epubsearch/morpho_engines/pymorphy2engine.py
epubsearcher/epubsearch/search_engines/__init__.py
epubsearcher/epubsearch/search_engines/baseengine.py
epubsearcher/epubsearch/search_engines/cheshire3engine.py
epubsearcher/epubsearch/search_engines/whooshengine.py