Metadata-Version: 1.0
Name: epubsearcher
Version: 0.1.5
Summary: Search selected word in epub book.
Home-page: https://bitbucket.org/Infernion/epubsearcher/overview
Author: Sergiy Khalymon
Author-email: sergiykhalimon@gmail.com
License: MIT
Platform: UNKNOWN
